MessageCleaner/__init__.py
MessageCleaner/abbreviations.json
MessageCleaner/cleaner.py
MessageCleaner/portuguese_errors.json
MessageCleaner/preprocessor.py
MessageCleaner/smalltalks.py
MessageCleaner/dictionaries/abbreviations.json
MessageCleaner/dictionaries/portuguese_errors.json
TakeMessageCleaner-1.1.4.dist-info/LICENSE
TakeMessageCleaner-1.1.4.dist-info/METADATA
TakeMessageCleaner-1.1.4.dist-info/WHEEL
TakeMessageCleaner-1.1.4.dist-info/top_level.txt
TakeMessageCleaner-1.1.4.dist-info/RECORD
