Metadata-Version: 2.1
Name: TakeMessageCleaner
Version: 1.1.4
Summary: TakeMessageCleaner is a tool for pre processing messages
Home-page: https://github.com/karinatk/TakeMessageCleaner
Author: Karina Tiemi Kato
Author-email: karinatkato@gmail.com
License: UNKNOWN
Keywords: Pre processing
Platform: UNKNOWN
Classifier: Programming Language :: Python :: 3
Classifier: License :: OSI Approved :: MIT License
Classifier: Operating System :: OS Independent
Requires-Dist: requests (==2.21.0)
Requires-Dist: emoji (==0.5.1)
Requires-Dist: Unidecode (==1.0.23)
Requires-Dist: setuptools (==40.2.0)
Requires-Dist: pandas
Requires-Dist: numpy
